simsogui/Configuration.py
simsogui/Gantt.py
simsogui/QCopyTableWidget.py
simsogui/QxtSpanSlider.py
simsogui/SimulationTab.py
simsogui/SimulatorWindow.py
simsogui/TaskGenerator.py
simsogui/__init__.py
simsogui/ModelWindow/AddRemoveButtonBar.py
simsogui/ModelWindow/CachesTab.py
simsogui/ModelWindow/CustomFieldsEditor.py
simsogui/ModelWindow/GeneralTab.py
simsogui/ModelWindow/ModelWindow.py
simsogui/ModelWindow/ProcessorsTab.py
simsogui/ModelWindow/SchedulerTab.py
simsogui/ModelWindow/Tab.py
simsogui/ModelWindow/TasksTab.py
simsogui/ModelWindow/__init__.py
simsogui/results/LoadTab.py
simsogui/results/Logs.py
simsogui/results/MetricsWindow.py
simsogui/results/ProcessorsTab.py
simsogui/results/SchedulerTab.py
simsogui/results/TasksTab.py
simsogui/results/__init__.py
simsogui-0.9.dist-info/COPYING.txt
simsogui-0.9.dist-info/METADATA
simsogui-0.9.dist-info/WHEEL
simsogui-0.9.dist-info/entry_points.txt
simsogui-0.9.dist-info/top_level.txt
simsogui-0.9.dist-info/RECORD
